pynamodb_extended/__init__.py
pynamodb_extended-0.1.0.dist-info/METADATA
pynamodb_extended-0.1.0.dist-info/WHEEL
pynamodb_extended-0.1.0.dist-info/RECORD
